tox_poetry.py
tox_poetry-0.5.0.dist-info/LICENSE
tox_poetry-0.5.0.dist-info/METADATA
tox_poetry-0.5.0.dist-info/WHEEL
tox_poetry-0.5.0.dist-info/entry_points.txt
tox_poetry-0.5.0.dist-info/top_level.txt
tox_poetry-0.5.0.dist-info/RECORD
