Metadata-Version: 2.1
Name: tox-poetry
Version: 0.5.0
Summary: Tox poetry plugin
Home-page: https://github.com/tkukushkin/tox-poetry
Author: Timofey Kukushkin
Author-email: tima@kukushkin.me
License: MIT
Project-URL: Source, https://github.com/tkukushkin/tox-poetry
Classifier: Development Status :: 4 - Beta
Classifier: Framework :: tox
Classifier: Intended Audience :: Developers
Classifier: Topic :: Software Development :: Testing
Classifier: Programming Language :: Python
Classifier: Programming Language :: Python :: 2
Classifier: Programming Language :: Python :: 2.7
Classifier: Programming Language :: Python :: 3
Classifier: Programming Language :: Python :: 3.6
Classifier: Programming Language :: Python :: 3.7
Classifier: Programming Language :: Python :: 3.8
Classifier: Programming Language :: Python :: 3.9
Classifier: Programming Language :: Python :: Implementation :: CPython
Classifier: Programming Language :: Python :: Implementation :: PyPy
Classifier: Operating System :: OS Independent
Classifier: License :: OSI Approved :: MIT License
License-File: LICENSE
Requires-Dist: pluggy
Requires-Dist: toml
Requires-Dist: tox (==3.15.1) ; python_version < "3"
Requires-Dist: tox (<4,>=3.7.0) ; python_version >= "3"
Provides-Extra: test
Requires-Dist: coverage ; extra == 'test'
Requires-Dist: pytest ; extra == 'test'
Requires-Dist: pycodestyle ; (python_version >= "3.9") and extra == 'test'
Requires-Dist: pylint ; (python_version >= "3.9") and extra == 'test'
